{"sections":[{"curriculum_id":"02324","title_code":"012","dept_name":"GEOL","catalog_number":"411","catalog_suffix":null,"section_number":"001","fixed_or_variable":"F","credit_hours":"3.00","minimum_credit_hours":"3.00","honors":null,"section_type":"DAY","credit_type":"S","start_date":"2019-09-03","end_date":"2019-12-12","year_term":"20195","instructors":[{"person_id":"612203792","byu_id":"046866186","net_id":"jr22","surname":"Radebaugh","sort_name":"Radebaugh, Jani","rest_of_name":"Jani","preferred_first_name":"Jani","phone_number":null,"attribute_type":"PRIMARY","year_term":"20195","curriculum_id":"02324","title_code":"012","section_number":"001","dept_name":"GEOL","catalog_number":"411","catalog_suffix":null,"fixed_or_variable":"F","credit_hours":"3.00","minimum_credit_hours":"3.00","honors":null,"credit_type":"S","section_type":"DAY"}],"times":[{"begin_time":"1335","end_time":"1450","building":"ESC","room":"C295","sequence_number":"4","mon":"","tue":"T","wed":"","thu":"R","fri":"","sat":"","sun":""}],"headers":[],"availability":{"seats_available":"19","class_size":"25","waitlist_size":"0"}}],"catalog":{"curriculum_id":"02324","title_code":"012","effective_date":"2014-09-02 00:00:00","expired_date":"2999-12-31 00:00:00","effective_year_term":"20145","expired_year_term":"29995","dept_name":"GEOL","catalog_number":"411","description":"Interpretive analysis of landforms and their geologic significance. Use of aerial/satellite images of Earth and other planets, topographic/bathymetric maps, multi-wavelength image data.  Field trips.","note":null,"offered":null,"prerequisite":"Geol 111 or Geol 330.","recommended":null,"title":"Geomorphology and Remote Sensing.","credit_hours":"3","lecture_hours":"3","lab_hours":"0","honors_approved":"N","when_taught":"Fall"},"dept_headers":[],"course_headers":[]}