{"sections":[{"curriculum_id":"05631","title_code":"001","dept_name":"STAT","catalog_number":"666","catalog_suffix":null,"section_number":"001","fixed_or_variable":"F","credit_hours":"3.00","minimum_credit_hours":"3.00","honors":null,"section_type":"DAY","credit_type":"S","start_date":"2019-09-03","end_date":"2019-12-12","year_term":"20195","instructors":[{"person_id":"067205852","byu_id":"491867242","net_id":"wfc1970","surname":"Christensen","sort_name":"Christensen, William F","rest_of_name":"William F","preferred_first_name":"William","phone_number":null,"attribute_type":"PRIMARY","year_term":"20195","curriculum_id":"05631","title_code":"001","section_number":"001","dept_name":"STAT","catalog_number":"666","catalog_suffix":null,"fixed_or_variable":"F","credit_hours":"3.00","minimum_credit_hours":"3.00","honors":null,"credit_type":"S","section_type":"DAY"}],"times":[{"begin_time":"1335","end_time":"1450","building":"JKB","room":"1106","sequence_number":"1","mon":"","tue":"T","wed":"","thu":"R","fri":"","sat":"","sun":""}],"headers":[],"availability":{"seats_available":"1","class_size":"15","waitlist_size":"0"}}],"catalog":{"curriculum_id":"05631","title_code":"001","effective_date":"2010-08-30 00:00:00","expired_date":"2999-12-31 00:00:00","effective_year_term":"20105","expired_year_term":"29995","dept_name":"STAT","catalog_number":"666","description":"Inference about mean vectors and covariance matrices; multivariate analysis of variance and regression; canonical correlation; discriminant, cluster, principal component, and factor analysis. ","note":null,"offered":null,"prerequisite":"Stat 535, 624, 642.","recommended":null,"title":"Multivariate Statistical Methods.","credit_hours":"3","lecture_hours":"3","lab_hours":"0","honors_approved":"N","when_taught":"Fall"},"dept_headers":[],"course_headers":[]}