{"sections":[{"curriculum_id":"02365","title_code":"003","dept_name":"GEOL","catalog_number":"552","catalog_suffix":null,"section_number":"001","fixed_or_variable":"F","credit_hours":"3.00","minimum_credit_hours":"3.00","honors":null,"section_type":"DAY","credit_type":"S","start_date":"2019-09-03","end_date":"2019-12-12","year_term":"20195","instructors":[{"person_id":"607202412","byu_id":"093421421","net_id":"ehc","surname":"Christiansen","sort_name":"Christiansen, Eric H","rest_of_name":"Eric H","preferred_first_name":"Eric","phone_number":null,"attribute_type":"PRIMARY","year_term":"20195","curriculum_id":"02365","title_code":"003","section_number":"001","dept_name":"GEOL","catalog_number":"552","catalog_suffix":null,"fixed_or_variable":"F","credit_hours":"3.00","minimum_credit_hours":"3.00","honors":null,"credit_type":"S","section_type":"DAY"}],"times":[{"begin_time":"0930","end_time":"1045","building":"ESC","room":"C153","sequence_number":"2","mon":"","tue":"T","wed":"","thu":"R","fri":"","sat":"","sun":""}],"headers":[],"availability":{"seats_available":"18","class_size":"24","waitlist_size":"0"}}],"catalog":{"curriculum_id":"02365","title_code":"003","effective_date":"2010-08-30 00:00:00","expired_date":"2999-12-31 00:00:00","effective_year_term":"20105","expired_year_term":"29995","dept_name":"GEOL","catalog_number":"552","description":"Origin and evolution of magmas, emphasizing trace element and isotopic compositions and intensive properties as calculated from mineral compositions.","note":null,"offered":null,"prerequisite":"Geol 352 or equivalent.","recommended":null,"title":"Igneous Petrology.","credit_hours":"3","lecture_hours":"4","lab_hours":"3","honors_approved":"N","when_taught":"Fall"},"dept_headers":[],"course_headers":[]}